webSpider_Douban/__init__.py
webSpider_Douban/webSpider_doubanFilms.py
webSpider_Douban/webSpider_doubleFilms.py
webSpider_Douban-2.2.0.dist-info/DESCRIPTION.rst
webSpider_Douban-2.2.0.dist-info/METADATA
webSpider_Douban-2.2.0.dist-info/RECORD
webSpider_Douban-2.2.0.dist-info/WHEEL
webSpider_Douban-2.2.0.dist-info/metadata.json
webSpider_Douban-2.2.0.dist-info/top_level.txt
