Metadata-Version: 2.0
Name: webSpider-Douban
Version: 2.2.0
Summary: Crawl Douban movie site and extract top ten latest films information
Home-page: https://github.com/v1siuol/webSpider_Douban
Author: v1siuol
Author-email: lvzh.louis2013@gmail.com
License: MIT
Keywords: web crawler
Platform: UNKNOWN
Classifier: Development Status :: 2 - Pre-Alpha
Classifier: Intended Audience :: Science/Research
Classifier: Topic :: Internet :: WWW/HTTP
Classifier: License :: OSI Approved :: MIT License
Classifier: Programming Language :: Python :: 3
Classifier: Programming Language :: Python :: 3.3
Classifier: Programming Language :: Python :: 3.4
Classifier: Programming Language :: Python :: 3.5
Requires-Dist: bs4
Requires-Dist: pandoc
